{
  "title": "Summer Art Camp! 5 Days of Artists and Painting Monet, Van Gogh, Matisse, & More",
  "type": "Multi-Day Course",
  "description": "In this 5 day class we will explore artists Monet, Matisse, Van Gogh, among others and then recreate paintings using crayon and watercolor. Students will have fun learning about the artists & creating their own art inspired by their work.",
  "teacher_name": "Kimberly R Moseler",
  "teacher_photo": "/Kimberly.jpg",
  "teacher_reviews": 469,
  "course_reviews": 5,
  "learners": 21,
  "course_photo": "/course.jpg"
}
